phoenix_wright_reverse/__init__.py
phoenix_wright_reverse/__version__.py
phoenix_wright_reverse/core.py
phoenix_wright_reverse-0.1.1.dist-info/LICENSE
phoenix_wright_reverse-0.1.1.dist-info/METADATA
phoenix_wright_reverse-0.1.1.dist-info/WHEEL
phoenix_wright_reverse-0.1.1.dist-info/top_level.txt
phoenix_wright_reverse-0.1.1.dist-info/RECORD
