Metadata-Version: 2.1
Name: phoenix-wright-reverse
Version: 0.1.1
Summary: phoenix_wright come feom <Phoenix Wright>
Home-page: https://pypi.org/project/phoenix-wright-reverse/
Author: chernic
Author-email: chernic@qq.com
License: MIT
Classifier: License :: OSI Approved :: MIT License
Classifier: Programming Language :: Python
Classifier: Programming Language :: Python :: 3
Classifier: Programming Language :: Python :: 3.6
Classifier: Programming Language :: Python :: Implementation :: CPython
Classifier: Programming Language :: Python :: Implementation :: PyPy
Requires-Python: >=3.10.0
License-File: LICENSE
Requires-Dist: akshare
Requires-Dist: aktools
Requires-Dist: PySide2
Requires-Dist: PyQt6
Requires-Dist: pandas
Requires-Dist: numpy
